Metadata-Version: 2.1
Name: odoo12-addon-stock-move-location
Version: 12.0.2.2.0
Summary: This module allows to move all stock in a stock location to an other one.
Home-page: https://github.com/OCA/stock-logistics-warehouse
Author: Julius Network Solutions, BCIM,Camptocamp,Odoo Community Association (OCA)
Author-email: support@odoo-community.org
License: AGPL-3
Platform: UNKNOWN
Classifier: Programming Language :: Python
Classifier: Framework :: Odoo
Classifier: Framework :: Odoo :: 12.0
Classifier: License :: OSI Approved :: GNU Affero General Public License v3
Requires-Python: >=3.5
Requires-Dist: odoo (<12.1dev,>=12.0a)
